{
  "UID": "NE:strmif._AM_OVERLAY_NOTIFY_FLAGS",
  "title": "_AM_OVERLAY_NOTIFY_FLAGS (strmif.h)",
  "description": "The AM_OVERLAY_NOTIFY_FLAGS enumeration indicates what the overlay has changed, or is about to change.",
  "helpviewer_keywords": [
    "AM_OVERLAY_NOTIFY_DEST_CHANGE",
    "AM_OVERLAY_NOTIFY_FLAGS",
    "AM_OVERLAY_NOTIFY_FLAGSEnumeration",
    "AM_OVERLAY_NOTIFY_SOURCE_CHANGE",
    "AM_OVERLAY_NOTIFY_VISIBLE_CHANGE",
    "_AM_OVERLAY_NOTIFY_FLAGS",
    "_AM_OVERLAY_NOTIFY_FLAGS enumeration [DirectShow]",
    "dshow.am_overlay_notify_flags",
    "strmif/AM_OVERLAY_NOTIFY_DEST_CHANGE",
    "strmif/AM_OVERLAY_NOTIFY_SOURCE_CHANGE",
    "strmif/AM_OVERLAY_NOTIFY_VISIBLE_CHANGE",
    "strmif/_AM_OVERLAY_NOTIFY_FLAGS"
  ],
  "old-location": "dshow\\am_overlay_notify_flags.htm",
  "tech.root": "dshow",
  "ms.assetid": "bc16714b-acee-4b5d-aa1d-6b53965183dc",
  "ms.date": "4/26/2023",
  "ms.keywords": "AM_OVERLAY_NOTIFY_DEST_CHANGE, AM_OVERLAY_NOTIFY_FLAGS, AM_OVERLAY_NOTIFY_FLAGSEnumeration, AM_OVERLAY_NOTIFY_SOURCE_CHANGE, AM_OVERLAY_NOTIFY_VISIBLE_CHANGE, _AM_OVERLAY_NOTIFY_FLAGS, _AM_OVERLAY_NOTIFY_FLAGS enumeration [DirectShow], dshow.am_overlay_notify_flags, strmif/AM_OVERLAY_NOTIFY_DEST_CHANGE, strmif/AM_OVERLAY_NOTIFY_SOURCE_CHANGE, strmif/AM_OVERLAY_NOTIFY_VISIBLE_CHANGE, strmif/_AM_OVERLAY_NOTIFY_FLAGS",
  "req.header": "strmif.h",
  "req.include-header": "Dshow.h",
  "req.target-type": "Windows",
  "req.target-min-winverclnt": null,
  "req.target-min-winversvr": null,
  "req.kmdf-ver": null,
  "req.umdf-ver": null,
  "req.ddi-compliance": null,
  "req.unicode-ansi": null,
  "req.idl": null,
  "req.max-support": null,
  "req.namespace": null,
  "req.assembly": null,
  "req.type-library": null,
  "req.lib": null,
  "req.dll": null,
  "req.irql": null,
  "targetos": "Windows",
  "req.typenames": null,
  "req.redist": null,
  "ms.custom": "19H1",
  "f1_keywords": [
    "_AM_OVERLAY_NOTIFY_FLAGS",
    "strmif/_AM_OVERLAY_NOTIFY_FLAGS"
  ],
  "dev_langs": [
    "c++"
  ],
  "topic_type": [
    "APIRef",
    "kbSyntax"
  ],
  "api_type": [
    "HeaderDef"
  ],
  "api_location": [
    "Strmif.h"
  ],
  "api_name": [
    "_AM_OVERLAY_NOTIFY_FLAGS"
  ]
}