{
  "UID": "NF:strmif.IFilterMapper2.UnregisterFilter",
  "title": "IFilterMapper2::UnregisterFilter (strmif.h)",
  "description": "The UnregisterFilter method removes filter information from the registry.",
  "helpviewer_keywords": [
    "IFilterMapper2 interface [DirectShow]",
    "UnregisterFilter method",
    "IFilterMapper2.UnregisterFilter",
    "IFilterMapper2::UnregisterFilter",
    "IFilterMapper2UnregisterFilter",
    "UnregisterFilter",
    "UnregisterFilter method [DirectShow]",
    "UnregisterFilter method [DirectShow]",
    "IFilterMapper2 interface",
    "dshow.ifiltermapper2_unregisterfilter",
    "strmif/IFilterMapper2::UnregisterFilter"
  ],
  "old-location": "dshow\\ifiltermapper2_unregisterfilter.htm",
  "tech.root": "dshow",
  "ms.assetid": "cfba764d-ec94-49a2-9aaf-2b107b742f83",
  "ms.date": "4/26/2023",
  "ms.keywords": "IFilterMapper2 interface [DirectShow],UnregisterFilter method, IFilterMapper2.UnregisterFilter, IFilterMapper2::UnregisterFilter, IFilterMapper2UnregisterFilter, UnregisterFilter, UnregisterFilter method [DirectShow], UnregisterFilter method [DirectShow],IFilterMapper2 interface, dshow.ifiltermapper2_unregisterfilter, strmif/IFilterMapper2::UnregisterFilter",
  "req.header": "strmif.h",
  "req.include-header": "Dshow.h",
  "req.target-type": "Windows",
  "req.target-min-winverclnt": "Windows 2000 Professional [desktop apps only]",
  "req.target-min-winversvr": "Windows 2000 Server [desktop apps only]",
  "req.kmdf-ver": null,
  "req.umdf-ver": null,
  "req.ddi-compliance": null,
  "req.unicode-ansi": null,
  "req.idl": null,
  "req.max-support": null,
  "req.namespace": null,
  "req.assembly": null,
  "req.type-library": null,
  "req.lib": "Strmiids.lib",
  "req.dll": null,
  "req.irql": null,
  "targetos": "Windows",
  "req.typenames": null,
  "req.redist": null,
  "ms.custom": "19H1",
  "f1_keywords": [
    "IFilterMapper2::UnregisterFilter",
    "strmif/IFilterMapper2::UnregisterFilter"
  ],
  "dev_langs": [
    "c++"
  ],
  "topic_type": [
    "APIRef",
    "kbSyntax"
  ],
  "api_type": [
    "COM"
  ],
  "api_location": [
    "Strmiids.lib",
    "Strmiids.dll"
  ],
  "api_name": [
    "IFilterMapper2.UnregisterFilter"
  ]
}