{
  "UID": "NF:xenroll.ICEnroll2.get_EnableT61DNEncoding",
  "title": "ICEnroll2::get_EnableT61DNEncoding (xenroll.h)",
  "description": "The EnableT61DNEncoding property of ICEnroll4 sets or retrieves a Boolean value that determines whether the distinguished name in the request is encoded as a T61 string instead of as a Unicode string. (Get)",
  "helpviewer_keywords": [
    "CEnroll object [Security]",
    "EnableT61DNEncoding property",
    "EnableT61DNEncoding property [Security]",
    "EnableT61DNEncoding property [Security]",
    "CEnroll object",
    "EnableT61DNEncoding property [Security]",
    "ICEnroll2 interface",
    "EnableT61DNEncoding property [Security]",
    "ICEnroll3 interface",
    "EnableT61DNEncoding property [Security]",
    "ICEnroll4 interface",
    "ICEnroll2 interface [Security]",
    "EnableT61DNEncoding property",
    "ICEnroll2.EnableT61DNEncoding",
    "ICEnroll2.get_EnableT61DNEncoding",
    "ICEnroll2::get_EnableT61DNEncoding",
    "ICEnroll2::put_EnableT61DNEncoding",
    "ICEnroll3 interface [Security]",
    "EnableT61DNEncoding property",
    "ICEnroll3.EnableT61DNEncoding",
    "ICEnroll3::get_EnableT61DNEncoding",
    "ICEnroll3::put_EnableT61DNEncoding",
    "ICEnroll4 interface [Security]",
    "EnableT61DNEncoding property",
    "ICEnroll4.EnableT61DNEncoding",
    "ICEnroll4::EnableT61DNEncoding",
    "ICEnroll4::get_EnableT61DNEncoding",
    "ICEnroll4::put_EnableT61DNEncoding",
    "get_EnableT61DNEncoding",
    "security.icenroll4_enablet61dnencoding",
    "xenroll/ICEnroll2::EnableT61DNEncoding",
    "xenroll/ICEnroll2::get_EnableT61DNEncoding",
    "xenroll/ICEnroll2::put_EnableT61DNEncoding",
    "xenroll/ICEnroll3::EnableT61DNEncoding",
    "xenroll/ICEnroll3::get_EnableT61DNEncoding",
    "xenroll/ICEnroll3::put_EnableT61DNEncoding",
    "xenroll/ICEnroll4::EnableT61DNEncoding",
    "xenroll/ICEnroll4::get_EnableT61DNEncoding",
    "xenroll/ICEnroll4::put_EnableT61DNEncoding"
  ],
  "old-location": "security\\icenroll4_enablet61dnencoding.htm",
  "tech.root": "security",
  "ms.assetid": "ff8fe103-0303-4f40-af25-efa50155c36f",
  "ms.date": "12/05/2018",
  "ms.keywords": "CEnroll object [Security],EnableT61DNEncoding property, EnableT61DNEncoding property [Security], EnableT61DNEncoding property [Security],CEnroll object, EnableT61DNEncoding property [Security],ICEnroll2 interface, EnableT61DNEncoding property [Security],ICEnroll3 interface, EnableT61DNEncoding property [Security],ICEnroll4 interface, ICEnroll2 interface [Security],EnableT61DNEncoding property, ICEnroll2.EnableT61DNEncoding, ICEnroll2.get_EnableT61DNEncoding, ICEnroll2::get_EnableT61DNEncoding, ICEnroll2::put_EnableT61DNEncoding, ICEnroll3 interface [Security],EnableT61DNEncoding property, ICEnroll3.EnableT61DNEncoding, ICEnroll3::get_EnableT61DNEncoding, ICEnroll3::put_EnableT61DNEncoding, ICEnroll4 interface [Security],EnableT61DNEncoding property, ICEnroll4.EnableT61DNEncoding, ICEnroll4::EnableT61DNEncoding, ICEnroll4::get_EnableT61DNEncoding, ICEnroll4::put_EnableT61DNEncoding, get_EnableT61DNEncoding, security.icenroll4_enablet61dnencoding, xenroll/ICEnroll2::EnableT61DNEncoding, xenroll/ICEnroll2::get_EnableT61DNEncoding, xenroll/ICEnroll2::put_EnableT61DNEncoding, xenroll/ICEnroll3::EnableT61DNEncoding, xenroll/ICEnroll3::get_EnableT61DNEncoding, xenroll/ICEnroll3::put_EnableT61DNEncoding, xenroll/ICEnroll4::EnableT61DNEncoding, xenroll/ICEnroll4::get_EnableT61DNEncoding, xenroll/ICEnroll4::put_EnableT61DNEncoding",
  "req.header": "xenroll.h",
  "req.include-header": null,
  "req.target-type": "Windows",
  "req.target-min-winverclnt": "Windows XP [desktop apps only]",
  "req.target-min-winversvr": "Windows Server 2003 [desktop apps only]",
  "req.kmdf-ver": null,
  "req.umdf-ver": null,
  "req.ddi-compliance": null,
  "req.unicode-ansi": null,
  "req.idl": null,
  "req.max-support": null,
  "req.namespace": null,
  "req.assembly": null,
  "req.type-library": null,
  "req.lib": "Uuid.lib",
  "req.dll": "Xenroll.dll",
  "req.irql": null,
  "targetos": "Windows",
  "req.typenames": null,
  "req.redist": null,
  "ms.custom": "19H1",
  "f1_keywords": [
    "ICEnroll2::get_EnableT61DNEncoding",
    "xenroll/ICEnroll2::get_EnableT61DNEncoding"
  ],
  "dev_langs": [
    "c++"
  ],
  "topic_type": [
    "APIRef",
    "kbSyntax"
  ],
  "api_type": [
    "COM"
  ],
  "api_location": [
    "Xenroll.dll"
  ],
  "api_name": [
    "ICEnroll4.EnableT61DNEncoding",
    "ICEnroll4.get_EnableT61DNEncoding",
    "ICEnroll4.put_EnableT61DNEncoding",
    "ICEnroll3.EnableT61DNEncoding",
    "ICEnroll3.get_EnableT61DNEncoding",
    "ICEnroll3.put_EnableT61DNEncoding",
    "ICEnroll2.EnableT61DNEncoding",
    "ICEnroll2.get_EnableT61DNEncoding",
    "ICEnroll2.put_EnableT61DNEncoding",
    "CEnroll.EnableT61DNEncoding"
  ]
}