{
  "UID": "NS:ntifs._ACE_HEADER",
  "title": "_ACE_HEADER (ntifs.h)",
  "description": "The ACE_HEADER structure describes the type and size of an access-control entry (ACE).",
  "old-location": "ifsk\\ace_header.htm",
  "tech.root": "ifsk",
  "ms.date": "04/16/2018",
  "keywords": [
    "ACE_HEADER structure"
  ],
  "ms.keywords": "*PACE_HEADER, ACE_HEADER, ACE_HEADER structure [Installable File System Drivers], PACE_HEADER, PACE_HEADER structure pointer [Installable File System Drivers], _ACE_HEADER, ifsk.ace_header, ntifs/ACE_HEADER, ntifs/PACE_HEADER, securitystructures_a5aba00b-54fc-4356-9dc8-bf3d5dbe7f78.xml",
  "req.header": "ntifs.h",
  "req.include-header": "Ntifs.h",
  "req.target-type": "Windows",
  "req.target-min-winverclnt": null,
  "req.target-min-winversvr": null,
  "req.kmdf-ver": null,
  "req.umdf-ver": null,
  "req.ddi-compliance": null,
  "req.unicode-ansi": null,
  "req.idl": null,
  "req.max-support": null,
  "req.namespace": null,
  "req.assembly": null,
  "req.type-library": null,
  "req.lib": null,
  "req.dll": null,
  "req.irql": null,
  "targetos": "Windows",
  "req.typenames": "ACE_HEADER",
  "f1_keywords": [
    "_ACE_HEADER",
    "ntifs/_ACE_HEADER",
    "ACE_HEADER",
    "ntifs/ACE_HEADER"
  ],
  "topic_type": [
    "APIRef",
    "kbSyntax"
  ],
  "api_type": [
    "HeaderDef"
  ],
  "api_location": [
    "ntifs.h"
  ],
  "api_name": [
    "_ACE_HEADER",
    "ACE_HEADER"
  ]
}