{
  "title": "D3DX_R16G16_SNORM_to_FLOAT2 function",
  "description": "Unpacks DXGI\\_FORMAT\\_R16G16\\_SNORM shader data to an XMFLOAT2.",
  "ms.assetid": "b54df555-b71f-46cd-8be7-34de785d15e2",
  "keywords": [
    "D3DX_R16G16_SNORM_to_FLOAT2 function HLSL"
  ],
  "topic_type": [
    "apiref"
  ],
  "api_name": [
    "D3DX_R16G16_SNORM_to_FLOAT2"
  ],
  "api_location": [
    "D3DX_DXGIFormatConvert.inl"
  ],
  "api_type": [
    "HeaderDef"
  ],
  "ms.topic": "reference",
  "ms.date": "05/31/2018",
  "_fuzzy_type": "function",
  "_fuzzy_ident": "D3DX_R16G16_SNORM_to_FLOAT2"
}