{
  "description": "Displays the Folder Sharing tab on the properties sheet for the specified folder.",
  "ms.assetid": "e622e4bb-eaf7-494f-b2a2-78ba1311a496",
  "title": "ShowShareFolderUI function",
  "ms.topic": "reference",
  "ms.date": "05/31/2018",
  "topic_type": [
    "APIRef",
    "kbSyntax"
  ],
  "api_name": [
    "ShowShareFolderUI",
    "ShowShareFolderUIW"
  ],
  "api_type": [
    "DllExport"
  ],
  "api_location": [
    "Ntshrui.dll"
  ],
  "_fuzzy_type": "function",
  "_fuzzy_ident": "ShowShareFolderUI"
}