{
  "UID": "NF:propsys.IPropertyStore.GetAt",
  "title": "IPropertyStore::GetAt (propsys.h)",
  "description": "Gets a property key from the property array of an item.",
  "helpviewer_keywords": [
    "GetAt",
    "GetAt (IPropertyStore)",
    "GetAt method [Audio Devices]",
    "GetAt method [Audio Devices]",
    "IPropertyStore interface",
    "IPropertyStore interface [Audio Devices]",
    "GetAt method",
    "IPropertyStore.GetAt",
    "IPropertyStore::GetAt",
    "audio.ipropertystore_getat",
    "audio_syseffects_r_3a52a0be-2e51-468f-9a93-86bd242b422e.xml",
    "propsys/IPropertyStore::GetAt"
  ],
  "old-location": "audio\\ipropertystore_getat.htm",
  "tech.root": "audio",
  "ms.assetid": "4f93949a-d5d5-4fbf-8538-6171861e5884",
  "ms.date": "12/05/2018",
  "ms.keywords": "GetAt, GetAt (IPropertyStore), GetAt method [Audio Devices], GetAt method [Audio Devices],IPropertyStore interface, IPropertyStore interface [Audio Devices],GetAt method, IPropertyStore.GetAt, IPropertyStore::GetAt, audio.ipropertystore_getat, audio_syseffects_r_3a52a0be-2e51-468f-9a93-86bd242b422e.xml, propsys/IPropertyStore::GetAt",
  "req.header": "propsys.h",
  "req.include-header": null,
  "req.target-type": "Universal",
  "req.target-min-winverclnt": "Available with Windows Vista and later versions of the Windows operating system.",
  "req.target-min-winversvr": null,
  "req.kmdf-ver": null,
  "req.umdf-ver": null,
  "req.ddi-compliance": null,
  "req.unicode-ansi": null,
  "req.idl": null,
  "req.max-support": null,
  "req.namespace": null,
  "req.assembly": null,
  "req.type-library": null,
  "req.lib": "Propsys.idl",
  "req.dll": null,
  "req.irql": "All levels",
  "targetos": "Windows",
  "req.typenames": null,
  "req.redist": null,
  "ms.custom": "19H1",
  "f1_keywords": [
    "IPropertyStore::GetAt",
    "propsys/IPropertyStore::GetAt"
  ],
  "dev_langs": [
    "c++"
  ],
  "topic_type": [
    "APIRef",
    "kbSyntax"
  ],
  "api_type": [
    "COM"
  ],
  "api_location": [
    "Propsys.idl",
    "Propsys.idl.dll"
  ],
  "api_name": [
    "IPropertyStore.GetAt"
  ]
}