{
  "UID": "NS:dcomptypes.tagCOMPOSITION_TARGET_ID",
  "tech.root": "directcomp",
  "title": "COMPOSITION_TARGET_ID",
  "ms.date": "06/24/2021",
  "targetos": "Windows",
  "description": "Contains information about a composition render target.",
  "prerelease": false,
  "req.construct-type": "structure",
  "req.ddi-compliance": null,
  "req.dll": null,
  "req.header": "dcomptypes.h",
  "req.include-header": null,
  "req.kmdf-ver": null,
  "req.lib": null,
  "req.max-support": null,
  "req.redist": null,
  "req.target-min-winverclnt": "Windows Build 22000",
  "req.target-min-winversvr": "Windows Build 22000",
  "req.target-type": null,
  "req.typenames": "COMPOSITION_TARGET_ID",
  "req.umdf-ver": null,
  "req.unicode-ansi": null,
  "topic_type": [
    "apiref"
  ],
  "api_type": [
    "HeaderDef"
  ],
  "api_location": [
    "dcomptypes.h"
  ],
  "api_name": [
    "tagCOMPOSITION_TARGET_ID",
    "COMPOSITION_TARGET_ID"
  ],
  "f1_keywords": [
    "tagCOMPOSITION_TARGET_ID",
    "dcomptypes/tagCOMPOSITION_TARGET_ID",
    "COMPOSITION_TARGET_ID",
    "dcomptypes/COMPOSITION_TARGET_ID"
  ],
  "dev_langs": [
    "c++"
  ]
}