{
  "UID": "NC:ndis.NDIS_PD_FREE_QUEUE",
  "title": "NDIS_PD_FREE_QUEUE (ndis.h)",
  "description": "The PacketDirect (PD) platform calls a PD-capable miniport driver's NdisPDFreeQueue function to free a queue.",
  "old-location": "netvista\\ndispdfreequeue.htm",
  "tech.root": "netvista",
  "ms.date": "05/02/2018",
  "keywords": [
    "NDIS_PD_FREE_QUEUE callback function"
  ],
  "ms.keywords": "NDIS_PD_FREE_QUEUE, NDIS_PD_FREE_QUEUE callback, NdisPDFreeQueue, NdisPDFreeQueue callback function [Network Drivers Starting with Windows Vista], ndis/NdisPDFreeQueue, netvista.ndispdfreequeue",
  "req.header": "ndis.h",
  "req.include-header": null,
  "req.target-type": "Windows",
  "req.target-min-winverclnt": "Windows 10",
  "req.target-min-winversvr": "Windows Server 2016",
  "req.kmdf-ver": null,
  "req.umdf-ver": null,
  "req.ddi-compliance": null,
  "req.unicode-ansi": null,
  "req.idl": null,
  "req.max-support": null,
  "req.namespace": null,
  "req.assembly": null,
  "req.type-library": null,
  "req.lib": null,
  "req.dll": null,
  "req.irql": "PASSIVE_LEVEL",
  "targetos": "Windows",
  "req.typenames": null,
  "f1_keywords": [
    "NDIS_PD_FREE_QUEUE",
    "ndis/NDIS_PD_FREE_QUEUE"
  ],
  "topic_type": [
    "APIRef",
    "kbSyntax"
  ],
  "api_type": [
    "UserDefined"
  ],
  "api_location": [
    "Ndis.h"
  ],
  "api_name": [
    "NDIS_PD_FREE_QUEUE"
  ]
}