{
  "title": "RtmGetRouteAge function (Rtm.h)",
  "description": "The RtmGetRouteAge function returns the age of a route. The age is the time, in seconds, since it was created or last updated.",
  "ms.assetid": "93052412-227f-4c9e-978b-3ec4bde4a256",
  "keywords": [
    "RtmGetRouteAge function RAS"
  ],
  "topic_type": [
    "apiref"
  ],
  "api_name": [
    "RtmGetRouteAge"
  ],
  "api_location": [
    "Rtm.dll"
  ],
  "api_type": [
    "DllExport"
  ],
  "ms.topic": "reference",
  "ms.date": "05/31/2018",
  "_fuzzy_type": "function",
  "_fuzzy_ident": "RtmGetRouteAge",
  "_fuzzy_header": "rtm.h"
}