{
  "UID": "NF:emptyvc.IEmptyVolumeCache.Initialize",
  "title": "IEmptyVolumeCache::Initialize (emptyvc.h)",
  "description": "Initializes the disk cleanup handler, based on the information stored under the specified registry key.",
  "helpviewer_keywords": [
    "EVCF_DONTSHOWIFZERO",
    "EVCF_ENABLEBYDEFAULT",
    "EVCF_ENABLEBYDEFAULT_AUTO",
    "EVCF_HASSETTINGS",
    "EVCF_OUTOFDISKSPACE",
    "EVCF_REMOVEFROMLIST",
    "EVCF_SETTINGSMODE",
    "IEmptyVolumeCache interface [Legacy Windows Environment Features]",
    "Initialize method",
    "IEmptyVolumeCache.Initialize",
    "IEmptyVolumeCache::Initialize",
    "Initialize",
    "Initialize method [Legacy Windows Environment Features]",
    "Initialize method [Legacy Windows Environment Features]",
    "IEmptyVolumeCache interface",
    "These flags can be passed by the handler back to the disk cleanup manager:",
    "These flags can be passed in to the object:",
    "_win32_IEmptyVolumeCache_Initialize",
    "emptyvc/IEmptyVolumeCache::Initialize",
    "lwef.iemptyvolumecache_initialize",
    "shell.iemptyvolumecache_initialize"
  ],
  "old-location": "lwef\\iemptyvolumecache_initialize.htm",
  "tech.root": "lwef",
  "ms.assetid": "e0d66c58-6963-4694-984f-6f4a710d08c0",
  "ms.date": "12/05/2018",
  "ms.keywords": "EVCF_DONTSHOWIFZERO, EVCF_ENABLEBYDEFAULT, EVCF_ENABLEBYDEFAULT_AUTO, EVCF_HASSETTINGS, EVCF_OUTOFDISKSPACE, EVCF_REMOVEFROMLIST, EVCF_SETTINGSMODE, IEmptyVolumeCache interface [Legacy Windows Environment Features],Initialize method, IEmptyVolumeCache.Initialize, IEmptyVolumeCache::Initialize, Initialize, Initialize method [Legacy Windows Environment Features], Initialize method [Legacy Windows Environment Features],IEmptyVolumeCache interface, These flags can be passed by the handler back to the disk cleanup manager:, These flags can be passed in to the object:, _win32_IEmptyVolumeCache_Initialize, emptyvc/IEmptyVolumeCache::Initialize, lwef.iemptyvolumecache_initialize, shell.iemptyvolumecache_initialize",
  "req.header": "emptyvc.h",
  "req.include-header": null,
  "req.target-type": "Windows",
  "req.target-min-winverclnt": "Windows 2000 Professional, Windows XP [desktop apps only]",
  "req.target-min-winversvr": "Windows Server 2003 [desktop apps only]",
  "req.kmdf-ver": null,
  "req.umdf-ver": null,
  "req.ddi-compliance": null,
  "req.unicode-ansi": null,
  "req.idl": null,
  "req.max-support": null,
  "req.namespace": null,
  "req.assembly": null,
  "req.type-library": null,
  "req.lib": null,
  "req.dll": "Shell32.dll (version 5.0 or later)",
  "req.irql": null,
  "targetos": "Windows",
  "req.typenames": null,
  "req.redist": null,
  "ms.custom": "19H1",
  "f1_keywords": [
    "IEmptyVolumeCache::Initialize",
    "emptyvc/IEmptyVolumeCache::Initialize"
  ],
  "dev_langs": [
    "c++"
  ],
  "topic_type": [
    "APIRef",
    "kbSyntax"
  ],
  "api_type": [
    "COM"
  ],
  "api_location": [
    "Shell32.dll"
  ],
  "api_name": [
    "IEmptyVolumeCache.Initialize"
  ]
}