{
  "UID": "NF:msinkaut.IInkDrawingAttributes.put_PenTip",
  "title": "IInkDrawingAttributes::put_PenTip (msinkaut.h)",
  "description": "Gets or sets a value that indicates which pen tip to use when drawing ink that is associated with this InkDrawingAttributes object. (Put)",
  "helpviewer_keywords": [
    "13e3c2dc-99a4-4643-b8b2-48586b0eb2f0",
    "IInkDrawingAttributes interface [Tablet PC]",
    "PenTip property",
    "IInkDrawingAttributes.PenTip",
    "IInkDrawingAttributes.put_PenTip",
    "IInkDrawingAttributes::PenTip",
    "IInkDrawingAttributes::get_PenTip",
    "IInkDrawingAttributes::put_PenTip",
    "InkDrawingAttributes.get_PenTip",
    "InkDrawingAttributes.put_PenTip",
    "PenTip property [Tablet PC]",
    "PenTip property [Tablet PC]",
    "IInkDrawingAttributes interface",
    "get_PenTip",
    "msinkaut/IInkDrawingAttributes::PenTip",
    "msinkaut/IInkDrawingAttributes::get_PenTip",
    "msinkaut/IInkDrawingAttributes::put_PenTip",
    "put_PenTip",
    "tablet.inkdrawingattributes_pentip"
  ],
  "old-location": "tablet\\inkdrawingattributes_pentip.htm",
  "tech.root": "tablet",
  "ms.assetid": "13e3c2dc-99a4-4643-b8b2-48586b0eb2f0",
  "ms.date": "12/05/2018",
  "ms.keywords": "13e3c2dc-99a4-4643-b8b2-48586b0eb2f0, IInkDrawingAttributes interface [Tablet PC],PenTip property, IInkDrawingAttributes.PenTip, IInkDrawingAttributes.put_PenTip, IInkDrawingAttributes::PenTip, IInkDrawingAttributes::get_PenTip, IInkDrawingAttributes::put_PenTip, InkDrawingAttributes.get_PenTip, InkDrawingAttributes.put_PenTip, PenTip property [Tablet PC], PenTip property [Tablet PC],IInkDrawingAttributes interface, get_PenTip, msinkaut/IInkDrawingAttributes::PenTip, msinkaut/IInkDrawingAttributes::get_PenTip, msinkaut/IInkDrawingAttributes::put_PenTip, put_PenTip, tablet.inkdrawingattributes_pentip",
  "req.header": "msinkaut.h",
  "req.include-header": null,
  "req.target-type": "Windows",
  "req.target-min-winverclnt": "Windows XP Tablet PC Edition [desktop apps only]",
  "req.target-min-winversvr": "None supported",
  "req.kmdf-ver": null,
  "req.umdf-ver": null,
  "req.ddi-compliance": null,
  "req.unicode-ansi": null,
  "req.idl": null,
  "req.max-support": null,
  "req.namespace": null,
  "req.assembly": null,
  "req.type-library": null,
  "req.lib": "InkObj.dll",
  "req.dll": null,
  "req.irql": null,
  "targetos": "Windows",
  "req.typenames": null,
  "req.redist": null,
  "ms.custom": "19H1",
  "f1_keywords": [
    "IInkDrawingAttributes::put_PenTip",
    "msinkaut/IInkDrawingAttributes::put_PenTip"
  ],
  "dev_langs": [
    "c++"
  ],
  "topic_type": [
    "APIRef",
    "kbSyntax"
  ],
  "api_type": [
    "COM"
  ],
  "api_location": [
    "InkObj.dll",
    "InkObj.dll.dll"
  ],
  "api_name": [
    "IInkDrawingAttributes.PenTip",
    "IInkDrawingAttributes.get_PenTip",
    "IInkDrawingAttributes.put_PenTip",
    "InkDrawingAttributes.get_PenTip",
    "InkDrawingAttributes.put_PenTip"
  ]
}