{
  "UID": "NF:wudfddi.IWDFIoRequest2.RetrieveOutputBuffer",
  "title": "IWDFIoRequest2::RetrieveOutputBuffer (wudfddi.h)",
  "description": "The RequestRetrieveOutputBuffer method retrieves an I/O request's output buffer.",
  "old-location": "wdf\\iwdfiorequest2_retrieveoutputbuffer.htm",
  "tech.root": "wdf",
  "ms.date": "02/26/2018",
  "keywords": [
    "IWDFIoRequest2::RetrieveOutputBuffer"
  ],
  "ms.keywords": "IWDFIoRequest2 interface,RetrieveOutputBuffer method, IWDFIoRequest2.RetrieveOutputBuffer, IWDFIoRequest2::RetrieveOutputBuffer, RetrieveOutputBuffer, RetrieveOutputBuffer method, RetrieveOutputBuffer method,IWDFIoRequest2 interface, UMDFRequestObjectRef_895f34da-95f3-4256-a049-0221887da5e1.xml, umdf.iwdfiorequest2_retrieveoutputbuffer, wdf.iwdfiorequest2_retrieveoutputbuffer, wudfddi/IWDFIoRequest2::RetrieveOutputBuffer",
  "req.header": "wudfddi.h",
  "req.include-header": "Wudfddi.h",
  "req.target-type": "Desktop",
  "req.target-min-winverclnt": null,
  "req.target-min-winversvr": null,
  "req.kmdf-ver": null,
  "req.umdf-ver": 1.9,
  "req.ddi-compliance": null,
  "req.unicode-ansi": null,
  "req.idl": null,
  "req.max-support": "Unavailable in UMDF 2.0 and later.",
  "req.namespace": null,
  "req.assembly": null,
  "req.type-library": null,
  "req.lib": null,
  "req.dll": "WUDFx.dll",
  "req.irql": null,
  "targetos": "Windows",
  "req.typenames": null,
  "f1_keywords": [
    "IWDFIoRequest2::RetrieveOutputBuffer",
    "wudfddi/IWDFIoRequest2::RetrieveOutputBuffer"
  ],
  "topic_type": [
    "APIRef",
    "kbSyntax"
  ],
  "api_type": [
    "COM"
  ],
  "api_location": [
    "WUDFx.dll"
  ],
  "api_name": [
    "IWDFIoRequest2::RetrieveOutputBuffer"
  ]
}