{
  "description": "The PORT\\_INFO\\_2 structure identifies a supported printer port.",
  "ms.assetid": "93675294-61d4-40e4-b84c-f252978e0285",
  "title": "PORT_INFO_2 structure (Winspool.h)",
  "ms.topic": "reference",
  "ms.date": "05/31/2018",
  "topic_type": [
    "APIRef",
    "kbSyntax"
  ],
  "api_name": [
    "PORT_INFO_2",
    "_PORT_INFO_2A",
    "_PORT_INFO_2W"
  ],
  "api_type": [
    "HeaderDef"
  ],
  "api_location": [
    "Winspool.h"
  ],
  "_fuzzy_type": "structure",
  "_fuzzy_ident": "PORT_INFO_2",
  "_fuzzy_header": "winspool.h"
}