{
  "UID": "NS:ntddvdeo._GAMMA_RAMP_RGB256x3x16",
  "title": "GAMMA_RAMP_RGB256x3x16",
  "description": "Gamma ramp RGB 256x3x16.",
  "tech.root": "display",
  "ms.date": "04/04/2019",
  "keywords": [
    "GAMMA_RAMP_RGB256x3x16 structure"
  ],
  "ms.keywords": "GAMMA_RAMP_RGB256x3x16, GAMMA_RAMP_RGB256x3x16,",
  "req.header": "ntddvdeo.h",
  "req.include-header": null,
  "req.target-type": null,
  "req.target-min-winverclnt": "Windows 10, version 1903",
  "req.target-min-winversvr": null,
  "req.kmdf-ver": null,
  "req.umdf-ver": null,
  "req.lib": null,
  "req.dll": null,
  "req.ddi-compliance": null,
  "req.unicode-ansi": null,
  "req.max-support": null,
  "req.typenames": "GAMMA_RAMP_RGB256x3x16",
  "targetos": "Windows",
  "ms.custom": "19H1",
  "f1_keywords": [
    "_GAMMA_RAMP_RGB256x3x16",
    "ntddvdeo/_GAMMA_RAMP_RGB256x3x16",
    "GAMMA_RAMP_RGB256x3x16",
    "ntddvdeo/GAMMA_RAMP_RGB256x3x16"
  ],
  "topic_type": [
    "apiref"
  ],
  "api_type": [
    "HeaderDef"
  ],
  "api_location": [
    "ntddvdeo.h"
  ],
  "api_name": [
    "_GAMMA_RAMP_RGB256x3x16",
    "GAMMA_RAMP_RGB256x3x16"
  ],
  "dev_langs": [
    "c++"
  ]
}