{
  "title": "HS_PLUGIN_DISCONNECT_FROM_NETWORK function",
  "description": "The HS_PLUGIN_DISCONNECT_FROM_NETWORK function notifies the plugin that the device will be disconnected from the network.",
  "keywords": [
    "typedef DWORD (WINAPI HS_PLUGIN_DISCONNECT_FROM_NETWORK) function Network Drivers Starting with Windows Vista"
  ],
  "ms.date": "07/31/2017",
  "ms.topic": "reference",
  "_fuzzy_type": "function",
  "_fuzzy_ident": "HS_PLUGIN_DISCONNECT_FROM_NETWORK",
  "_fuzzy_header": "hotspotoffloadplugin.h"
}