{
  "UID": "NF:tom.ITextPara2.IsEqual2",
  "title": "ITextPara2::IsEqual2 (tom.h)",
  "description": "Determines whether this text paragraph object has the same properties as the specified text paragraph object.",
  "helpviewer_keywords": [
    "ITextPara2 interface [Windows Controls]",
    "IsEqual2 method",
    "ITextPara2.IsEqual2",
    "ITextPara2::IsEqual2",
    "IsEqual2",
    "IsEqual2 method [Windows Controls]",
    "IsEqual2 method [Windows Controls]",
    "ITextPara2 interface",
    "controls.itextpara2_isequal2",
    "tom/ITextPara2::IsEqual2"
  ],
  "old-location": "controls\\itextpara2_isequal2.htm",
  "tech.root": "Controls",
  "ms.assetid": "7817b1bd-6ade-4145-90ff-54561a639dc9",
  "ms.date": "12/05/2018",
  "ms.keywords": "ITextPara2 interface [Windows Controls],IsEqual2 method, ITextPara2.IsEqual2, ITextPara2::IsEqual2, IsEqual2, IsEqual2 method [Windows Controls], IsEqual2 method [Windows Controls],ITextPara2 interface, controls.itextpara2_isequal2, tom/ITextPara2::IsEqual2",
  "req.header": "tom.h",
  "req.include-header": null,
  "req.target-type": "Windows",
  "req.target-min-winverclnt": "Windows 8 [desktop apps only]",
  "req.target-min-winversvr": "Windows Server 2012 [desktop apps only]",
  "req.kmdf-ver": null,
  "req.umdf-ver": null,
  "req.ddi-compliance": null,
  "req.unicode-ansi": null,
  "req.idl": null,
  "req.max-support": null,
  "req.namespace": null,
  "req.assembly": null,
  "req.type-library": null,
  "req.lib": null,
  "req.dll": "Msftedit.dll",
  "req.irql": null,
  "targetos": "Windows",
  "req.typenames": null,
  "req.redist": null,
  "ms.custom": "19H1",
  "f1_keywords": [
    "ITextPara2::IsEqual2",
    "tom/ITextPara2::IsEqual2"
  ],
  "dev_langs": [
    "c++"
  ],
  "topic_type": [
    "APIRef",
    "kbSyntax"
  ],
  "api_type": [
    "COM"
  ],
  "api_location": [
    "Msftedit.dll"
  ],
  "api_name": [
    "ITextPara2.IsEqual2"
  ]
}