{
  "UID": "NF:wdm.NtRecoverEnlistment",
  "title": "NtRecoverEnlistment function (wdm.h)",
  "description": "The ZwRecoverEnlistment routine initiates a recovery operation for the transaction that is associated with a specified enlistment.",
  "old-location": "kernel\\zwrecoverenlistment.htm",
  "tech.root": "kernel",
  "ms.date": "04/30/2018",
  "keywords": [
    "NtRecoverEnlistment function"
  ],
  "ms.keywords": "NtRecoverEnlistment, ZwRecoverEnlistment, ZwRecoverEnlistment routine [Kernel-Mode Driver Architecture], kernel.zwrecoverenlistment, ktm_ref_0a6564fb-c6d1-4b4b-a278-a1d78395c1b4.xml, wdm/NtRecoverEnlistment, wdm/ZwRecoverEnlistment",
  "req.header": "wdm.h",
  "req.include-header": "Wdm.h, Ntddk.h, Ntifs.h",
  "req.target-type": "Universal",
  "req.target-min-winverclnt": "Available in Windows Vista and later operating system versions.",
  "req.target-min-winversvr": null,
  "req.kmdf-ver": null,
  "req.umdf-ver": null,
  "req.ddi-compliance": "PowerIrpDDis, HwStorPortProhibitedDDIs",
  "req.unicode-ansi": null,
  "req.idl": null,
  "req.max-support": null,
  "req.namespace": null,
  "req.assembly": null,
  "req.type-library": null,
  "req.lib": "NtosKrnl.lib",
  "req.dll": "NtosKrnl.exe",
  "req.irql": "PASSIVE_LEVEL",
  "targetos": "Windows",
  "req.typenames": null,
  "f1_keywords": [
    "NtRecoverEnlistment",
    "wdm/NtRecoverEnlistment"
  ],
  "topic_type": [
    "APIRef",
    "kbSyntax"
  ],
  "api_type": [
    "DllExport"
  ],
  "api_location": [
    "NtosKrnl.exe"
  ],
  "api_name": [
    "NtRecoverEnlistment"
  ]
}