{
  "UID": "NF:identityprovider.IIdentityProvider.FindByUniqueID",
  "title": "IIdentityProvider::FindByUniqueID (identityprovider.h)",
  "description": "Retrieves a pointer to the IPropertyStore interface instance associated with the specified identity.",
  "helpviewer_keywords": [
    "FindByUniqueID",
    "FindByUniqueID method [Security]",
    "FindByUniqueID method [Security]",
    "IIdentityProvider interface",
    "IIdentityProvider interface [Security]",
    "FindByUniqueID method",
    "IIdentityProvider.FindByUniqueID",
    "IIdentityProvider::FindByUniqueID",
    "identityprovider/IIdentityProvider::FindByUniqueID",
    "security.iidentityprovider_findbyuniqueid"
  ],
  "old-location": "security\\iidentityprovider_findbyuniqueid.htm",
  "tech.root": "security",
  "ms.assetid": "26a0e247-0387-4455-9510-bd0e6adc0213",
  "ms.date": "12/05/2018",
  "ms.keywords": "FindByUniqueID, FindByUniqueID method [Security], FindByUniqueID method [Security],IIdentityProvider interface, IIdentityProvider interface [Security],FindByUniqueID method, IIdentityProvider.FindByUniqueID, IIdentityProvider::FindByUniqueID, identityprovider/IIdentityProvider::FindByUniqueID, security.iidentityprovider_findbyuniqueid",
  "req.header": "identityprovider.h",
  "req.include-header": null,
  "req.target-type": "Windows",
  "req.target-min-winverclnt": "Windows 7 [desktop apps only]",
  "req.target-min-winversvr": "Windows Server 2008 R2 [desktop apps only]",
  "req.kmdf-ver": null,
  "req.umdf-ver": null,
  "req.ddi-compliance": null,
  "req.unicode-ansi": null,
  "req.idl": "Identityprovider.idl",
  "req.max-support": null,
  "req.namespace": null,
  "req.assembly": null,
  "req.type-library": null,
  "req.lib": null,
  "req.dll": null,
  "req.irql": null,
  "targetos": "Windows",
  "req.typenames": null,
  "req.redist": null,
  "ms.custom": "19H1",
  "f1_keywords": [
    "IIdentityProvider::FindByUniqueID",
    "identityprovider/IIdentityProvider::FindByUniqueID"
  ],
  "dev_langs": [
    "c++"
  ],
  "topic_type": [
    "APIRef",
    "kbSyntax"
  ],
  "api_type": [
    "COM"
  ],
  "api_location": [
    "Identityprovider.h"
  ],
  "api_name": [
    "IIdentityProvider.FindByUniqueID"
  ]
}