{
  "UID": "NE:d3d12umddi.D3D12DDI_RANGED_BARRIER_FLAGS_0094",
  "tech.root": "display",
  "title": "D3D12DDI_RANGED_BARRIER_FLAGS_0094",
  "ms.date": "10/17/2022",
  "targetos": "Windows",
  "description": "Learn more about the D3D12DDI_RANGED_BARRIER_FLAGS_0094 enumeration.",
  "prerelease": false,
  "req.construct-type": "enumeration",
  "req.ddi-compliance": null,
  "req.header": "d3d12umddi.h",
  "req.include-header": null,
  "req.kmdf-ver": null,
  "req.max-support": null,
  "req.target-min-winverclnt": "Windows 11, version 24H2",
  "req.target-min-winversvr": null,
  "req.target-type": null,
  "req.typenames": null,
  "req.umdf-ver": null,
  "topic_type": [
    "apiref"
  ],
  "api_type": [
    "HeaderDef"
  ],
  "api_location": [
    "d3d12umddi.h"
  ],
  "api_name": [
    "D3D12DDI_RANGED_BARRIER_FLAGS_0094"
  ],
  "f1_keywords": [
    "D3D12DDI_RANGED_BARRIER_FLAGS_0094",
    "d3d12umddi/D3D12DDI_RANGED_BARRIER_FLAGS_0094"
  ],
  "dev_langs": [
    "c++"
  ],
  "helpviewer_keywords": [
    "D3D12DDI_RANGED_BARRIER_FLAGS_0094"
  ]
}