{
  "UID": "NF:dxgi1_2.IDXGIDevice2.ReclaimResources",
  "title": "IDXGIDevice2::ReclaimResources (dxgi1_2.h)",
  "description": "Restores access to resources that were previously offered by calling IDXGIDevice2::OfferResources.",
  "helpviewer_keywords": [
    "IDXGIDevice2 interface [DXGI]",
    "ReclaimResources method",
    "IDXGIDevice2.ReclaimResources",
    "IDXGIDevice2::ReclaimResources",
    "ReclaimResources",
    "ReclaimResources method [DXGI]",
    "ReclaimResources method [DXGI]",
    "IDXGIDevice2 interface",
    "direct3ddxgi.idxgidevice2_reclaimresources",
    "dxgi1_2/IDXGIDevice2::ReclaimResources"
  ],
  "old-location": "direct3ddxgi\\idxgidevice2_reclaimresources.htm",
  "tech.root": "direct3ddxgi",
  "ms.assetid": "30533605-0F5A-4D15-B01E-7C23E2AE775E",
  "ms.date": "12/05/2018",
  "ms.keywords": "IDXGIDevice2 interface [DXGI],ReclaimResources method, IDXGIDevice2.ReclaimResources, IDXGIDevice2::ReclaimResources, ReclaimResources, ReclaimResources method [DXGI], ReclaimResources method [DXGI],IDXGIDevice2 interface, direct3ddxgi.idxgidevice2_reclaimresources, dxgi1_2/IDXGIDevice2::ReclaimResources",
  "req.header": "dxgi1_2.h",
  "req.include-header": null,
  "req.target-type": "Windows",
  "req.target-min-winverclnt": "Windows 8 and Platform Update for Windows 7 [desktop apps \\| UWP apps]",
  "req.target-min-winversvr": "Windows Server 2012 and Platform Update for Windows Server 2008 R2 [desktop apps \\| UWP apps]",
  "req.kmdf-ver": null,
  "req.umdf-ver": null,
  "req.ddi-compliance": null,
  "req.unicode-ansi": null,
  "req.idl": null,
  "req.max-support": null,
  "req.namespace": null,
  "req.assembly": null,
  "req.type-library": null,
  "req.lib": "Dxgi.lib",
  "req.dll": null,
  "req.irql": null,
  "targetos": "Windows",
  "req.typenames": null,
  "req.redist": null,
  "ms.custom": "19H1",
  "f1_keywords": [
    "IDXGIDevice2::ReclaimResources",
    "dxgi1_2/IDXGIDevice2::ReclaimResources"
  ],
  "dev_langs": [
    "c++"
  ],
  "topic_type": [
    "APIRef",
    "kbSyntax"
  ],
  "api_type": [
    "COM"
  ],
  "api_location": [
    "Dxgi.lib",
    "Dxgi.dll"
  ],
  "api_name": [
    "IDXGIDevice2.ReclaimResources"
  ]
}