{
  "UID": "NF:dbgeng.IDebugEventCallbacks.SystemError",
  "title": "IDebugEventCallbacks::SystemError (dbgeng.h)",
  "description": "The SystemError callback method is called by the engine when a system error occurs in the target. This method belongs to the IDebugEventCallbacks interface.",
  "old-location": "debugger\\idebugeventcallbacks_systemerror.htm",
  "tech.root": "debugger",
  "ms.date": "05/03/2018",
  "keywords": [
    "IDebugEventCallbacks::SystemError"
  ],
  "ms.keywords": "ComCallbacks_a84628b9-4376-4ca0-883f-835d19e13d73.xml, IDebugEventCallbacks interface [Windows Debugging],SystemError method, IDebugEventCallbacks.SystemError, IDebugEventCallbacks::SystemError, SystemError, SystemError method [Windows Debugging], SystemError method [Windows Debugging],IDebugEventCallbacks interface, dbgeng/IDebugEventCallbacks::SystemError, debugger.idebugeventcallbacks_systemerror",
  "req.header": "dbgeng.h",
  "req.include-header": "Dbgeng.h",
  "req.target-type": "Desktop",
  "req.target-min-winverclnt": null,
  "req.target-min-winversvr": null,
  "req.kmdf-ver": null,
  "req.umdf-ver": null,
  "req.ddi-compliance": null,
  "req.unicode-ansi": null,
  "req.idl": null,
  "req.max-support": null,
  "req.namespace": null,
  "req.assembly": null,
  "req.type-library": null,
  "req.lib": null,
  "req.dll": null,
  "req.irql": null,
  "targetos": "Windows",
  "req.typenames": null,
  "f1_keywords": [
    "IDebugEventCallbacks::SystemError",
    "dbgeng/IDebugEventCallbacks::SystemError"
  ],
  "topic_type": [
    "APIRef",
    "kbSyntax"
  ],
  "api_type": [
    "COM"
  ],
  "api_location": [
    "dbgeng.h"
  ],
  "api_name": [
    "IDebugEventCallbacks::SystemError"
  ]
}