{
  "UID": "NF:dbgeng.IDebugRegisters2.GetInstructionOffset2",
  "title": "IDebugRegisters2::GetInstructionOffset2 (dbgeng.h)",
  "description": "The GetInstructionOffset2 method returns the location of the current thread's current instruction.",
  "old-location": "debugger\\getinstructionoffset2.htm",
  "tech.root": "debugger",
  "ms.date": "05/03/2018",
  "keywords": [
    "IDebugRegisters2::GetInstructionOffset2"
  ],
  "ms.keywords": "GetInstructionOffset2, GetInstructionOffset2 method [Windows Debugging], GetInstructionOffset2 method [Windows Debugging],IDebugRegisters2 interface, IDebugRegisters2 interface [Windows Debugging],GetInstructionOffset2 method, IDebugRegisters2.GetInstructionOffset2, IDebugRegisters2::GetInstructionOffset2, IDebugRegisters_92189e99-c8f6-4422-8421-62fe194a05b6.xml, dbgeng/IDebugRegisters2::GetInstructionOffset2, debugger.getinstructionoffset2",
  "req.header": "dbgeng.h",
  "req.include-header": "DbgEng.h",
  "req.target-type": "Desktop",
  "req.target-min-winverclnt": null,
  "req.target-min-winversvr": null,
  "req.kmdf-ver": null,
  "req.umdf-ver": null,
  "req.ddi-compliance": null,
  "req.unicode-ansi": null,
  "req.idl": null,
  "req.max-support": null,
  "req.namespace": null,
  "req.assembly": null,
  "req.type-library": null,
  "req.lib": null,
  "req.dll": null,
  "req.irql": null,
  "targetos": "Windows",
  "req.typenames": null,
  "f1_keywords": [
    "IDebugRegisters2::GetInstructionOffset2",
    "dbgeng/IDebugRegisters2::GetInstructionOffset2"
  ],
  "topic_type": [
    "APIRef",
    "kbSyntax"
  ],
  "api_type": [
    "COM"
  ],
  "api_location": [
    "dbgeng.h"
  ],
  "api_name": [
    "IDebugRegisters2::GetInstructionOffset2"
  ]
}