{
  "UID": "NF:dbgeng.IDebugControl3.RemoveAssemblyOptions",
  "title": "IDebugControl3::RemoveAssemblyOptions (dbgeng.h)",
  "description": "The RemoveAssemblyOptions method turns off some of the assembly and disassembly options.",
  "old-location": "debugger\\removeassemblyoptions.htm",
  "tech.root": "debugger",
  "ms.date": "05/03/2018",
  "keywords": [
    "IDebugControl3::RemoveAssemblyOptions"
  ],
  "ms.keywords": "IDebugControl3 interface [Windows Debugging],RemoveAssemblyOptions method, IDebugControl3.RemoveAssemblyOptions, IDebugControl3::RemoveAssemblyOptions, IDebugControl_8d971b27-ff9f-4097-a96a-68dabf08b200.xml, RemoveAssemblyOptions, RemoveAssemblyOptions method [Windows Debugging], RemoveAssemblyOptions method [Windows Debugging],IDebugControl3 interface, dbgeng/IDebugControl3::RemoveAssemblyOptions, debugger.removeassemblyoptions",
  "req.header": "dbgeng.h",
  "req.include-header": "Dbgeng.h",
  "req.target-type": "Desktop",
  "req.target-min-winverclnt": null,
  "req.target-min-winversvr": null,
  "req.kmdf-ver": null,
  "req.umdf-ver": null,
  "req.ddi-compliance": null,
  "req.unicode-ansi": null,
  "req.idl": null,
  "req.max-support": null,
  "req.namespace": null,
  "req.assembly": null,
  "req.type-library": null,
  "req.lib": null,
  "req.dll": null,
  "req.irql": null,
  "targetos": "Windows",
  "req.typenames": null,
  "f1_keywords": [
    "IDebugControl3::RemoveAssemblyOptions",
    "dbgeng/IDebugControl3::RemoveAssemblyOptions"
  ],
  "topic_type": [
    "APIRef",
    "kbSyntax"
  ],
  "api_type": [
    "COM"
  ],
  "api_location": [
    "dbgeng.h"
  ],
  "api_name": [
    "IDebugControl3::RemoveAssemblyOptions"
  ]
}