{
  "UID": "NE:sdoias._ATTRIBUTEFILTER",
  "title": "ATTRIBUTEFILTER (sdoias.h)",
  "description": "The usage cases for the NPS dictionary attributes.",
  "helpviewer_keywords": [
    "ATTRIBUTEFILTER",
    "ATTRIBUTEFILTER enumeration [Network Policy Server]",
    "ATTRIBUTE_FILTER_IEEE_802_1x",
    "ATTRIBUTE_FILTER_NONE",
    "ATTRIBUTE_FILTER_VPN_DIALUP",
    "nps.SDO_attributefilter",
    "sdo.attributefilter",
    "sdoias/ATTRIBUTEFILTER",
    "sdoias/ATTRIBUTE_FILTER_IEEE_802_1x",
    "sdoias/ATTRIBUTE_FILTER_NONE",
    "sdoias/ATTRIBUTE_FILTER_VPN_DIALUP"
  ],
  "old-location": "nps\\SDO_attributefilter.htm",
  "tech.root": "Nps",
  "ms.assetid": "7c90abe6-7a01-477d-b44d-6ae3ff1ef588",
  "ms.date": "12/05/2018",
  "ms.keywords": "ATTRIBUTEFILTER, ATTRIBUTEFILTER enumeration [Network Policy Server], ATTRIBUTE_FILTER_IEEE_802_1x, ATTRIBUTE_FILTER_NONE, ATTRIBUTE_FILTER_VPN_DIALUP, nps.SDO_attributefilter, sdo.attributefilter, sdoias/ATTRIBUTEFILTER, sdoias/ATTRIBUTE_FILTER_IEEE_802_1x, sdoias/ATTRIBUTE_FILTER_NONE, sdoias/ATTRIBUTE_FILTER_VPN_DIALUP",
  "req.header": "sdoias.h",
  "req.include-header": null,
  "req.target-type": "Windows",
  "req.target-min-winverclnt": "None supported",
  "req.target-min-winversvr": "Windows Server 2008",
  "req.kmdf-ver": null,
  "req.umdf-ver": null,
  "req.ddi-compliance": null,
  "req.unicode-ansi": null,
  "req.idl": "SdoIas.idl",
  "req.max-support": null,
  "req.namespace": null,
  "req.assembly": null,
  "req.type-library": null,
  "req.lib": null,
  "req.dll": null,
  "req.irql": null,
  "targetos": "Windows",
  "req.typenames": "ATTRIBUTEFILTER",
  "req.redist": null,
  "ms.custom": "19H1",
  "f1_keywords": [
    "_ATTRIBUTEFILTER",
    "sdoias/_ATTRIBUTEFILTER",
    "ATTRIBUTEFILTER",
    "sdoias/ATTRIBUTEFILTER"
  ],
  "dev_langs": [
    "c++"
  ],
  "topic_type": [
    "APIRef",
    "kbSyntax"
  ],
  "api_type": [
    "HeaderDef"
  ],
  "api_location": [
    "SdoIas.h"
  ],
  "api_name": [
    "ATTRIBUTEFILTER"
  ]
}