{
  "UID": "NF:dbgmodel.IModelObject.AddParentModel",
  "title": "IModelObject::AddParentModel (dbgmodel.h)",
  "description": "The AddParentModel method adds a new parent model to the given object.",
  "ms.date": "08/08/2018",
  "keywords": [
    "IModelObject::AddParentModel"
  ],
  "ms.keywords": "IModelObject::AddParentModel, AddParentModel, IModelObject.AddParentModel, IModelObject::AddParentModel, IModelObject.AddParentModel",
  "req.header": "dbgmodel.h",
  "req.include-header": null,
  "req.target-type": null,
  "req.target-min-winverclnt": null,
  "req.target-min-winversvr": null,
  "req.kmdf-ver": null,
  "req.umdf-ver": null,
  "req.lib": null,
  "req.dll": null,
  "req.irql": null,
  "req.ddi-compliance": null,
  "req.unicode-ansi": null,
  "req.idl": null,
  "req.max-support": null,
  "req.namespace": null,
  "req.assembly": null,
  "req.type-library": null,
  "targetos": "Windows",
  "tech.root": "debugger",
  "ms.custom": "RS5",
  "f1_keywords": [
    "IModelObject::AddParentModel",
    "dbgmodel/IModelObject::AddParentModel"
  ],
  "topic_type": [
    "apiref"
  ],
  "api_type": [
    "COM"
  ],
  "api_location": [
    "dbgmodel.h"
  ],
  "api_name": [
    "IModelObject::AddParentModel"
  ]
}