{
  "UID": "NF:ctfutb.ITfMenu.AddMenuItem",
  "title": "ITfMenu::AddMenuItem (ctfutb.h)",
  "description": "ITfMenu::AddMenuItem method",
  "helpviewer_keywords": [
    "AddMenuItem",
    "AddMenuItem method [Text Services Framework]",
    "AddMenuItem method [Text Services Framework]",
    "ITfMenu interface",
    "ITfMenu interface [Text Services Framework]",
    "AddMenuItem method",
    "ITfMenu.AddMenuItem",
    "ITfMenu::AddMenuItem",
    "_tsf_itfmenu_addmenuitem_ref",
    "ctfutb/ITfMenu::AddMenuItem",
    "tsf.itfmenu_addmenuitem"
  ],
  "old-location": "tsf\\itfmenu_addmenuitem.htm",
  "tech.root": "TSF",
  "ms.assetid": "c00048d1-d7c1-4ea3-a132-5f5aa570148f",
  "ms.date": "12/05/2018",
  "ms.keywords": "AddMenuItem, AddMenuItem method [Text Services Framework], AddMenuItem method [Text Services Framework],ITfMenu interface, ITfMenu interface [Text Services Framework],AddMenuItem method, ITfMenu.AddMenuItem, ITfMenu::AddMenuItem, _tsf_itfmenu_addmenuitem_ref, ctfutb/ITfMenu::AddMenuItem, tsf.itfmenu_addmenuitem",
  "req.header": "ctfutb.h",
  "req.include-header": null,
  "req.target-type": "Windows",
  "req.target-min-winverclnt": "Windows 2000 Professional [desktop apps only]",
  "req.target-min-winversvr": "Windows 2000 Server [desktop apps only]",
  "req.kmdf-ver": null,
  "req.umdf-ver": null,
  "req.ddi-compliance": null,
  "req.unicode-ansi": null,
  "req.idl": "Ctfutb.idl",
  "req.max-support": null,
  "req.namespace": null,
  "req.assembly": null,
  "req.type-library": null,
  "req.lib": null,
  "req.dll": "Msctf.dll",
  "req.irql": null,
  "targetos": "Windows",
  "req.typenames": null,
  "req.redist": "TSF 1.0 on Windows 2000 Professional",
  "ms.custom": "19H1",
  "f1_keywords": [
    "ITfMenu::AddMenuItem",
    "ctfutb/ITfMenu::AddMenuItem"
  ],
  "dev_langs": [
    "c++"
  ],
  "topic_type": [
    "APIRef",
    "kbSyntax"
  ],
  "api_type": [
    "COM"
  ],
  "api_location": [
    "Msctf.dll"
  ],
  "api_name": [
    "ITfMenu.AddMenuItem"
  ]
}