{
  "UID": "NF:d3d11_1.ID3D11VideoContext1.DecoderUpdateDownsampling",
  "title": "ID3D11VideoContext1::DecoderUpdateDownsampling (d3d11_1.h)",
  "description": "Updates the decoder downsampling parameters.",
  "helpviewer_keywords": [
    "DecoderUpdateDownsampling",
    "DecoderUpdateDownsampling method [Media Foundation]",
    "DecoderUpdateDownsampling method [Media Foundation]",
    "ID3D11VideoContext1 interface",
    "ID3D11VideoContext1 interface [Media Foundation]",
    "DecoderUpdateDownsampling method",
    "ID3D11VideoContext1.DecoderUpdateDownsampling",
    "ID3D11VideoContext1::DecoderUpdateDownsampling",
    "d3d11_1/ID3D11VideoContext1::DecoderUpdateDownsampling",
    "mf.id3d11videocontext1_decoderupdatedownsampling"
  ],
  "old-location": "mf\\id3d11videocontext1_decoderupdatedownsampling.htm",
  "tech.root": "mf",
  "ms.assetid": "A55D652B-9295-42E4-9A83-CAC467BEE68E",
  "ms.date": "12/05/2018",
  "ms.keywords": "DecoderUpdateDownsampling, DecoderUpdateDownsampling method [Media Foundation], DecoderUpdateDownsampling method [Media Foundation],ID3D11VideoContext1 interface, ID3D11VideoContext1 interface [Media Foundation],DecoderUpdateDownsampling method, ID3D11VideoContext1.DecoderUpdateDownsampling, ID3D11VideoContext1::DecoderUpdateDownsampling, d3d11_1/ID3D11VideoContext1::DecoderUpdateDownsampling, mf.id3d11videocontext1_decoderupdatedownsampling",
  "req.header": "d3d11_1.h",
  "req.include-header": null,
  "req.target-type": "Windows",
  "req.target-min-winverclnt": "Windows 10 [desktop apps only]",
  "req.target-min-winversvr": "Windows Server 2016 [desktop apps only]",
  "req.kmdf-ver": null,
  "req.umdf-ver": null,
  "req.ddi-compliance": null,
  "req.unicode-ansi": null,
  "req.idl": null,
  "req.max-support": null,
  "req.namespace": null,
  "req.assembly": null,
  "req.type-library": null,
  "req.lib": null,
  "req.dll": null,
  "req.irql": null,
  "targetos": "Windows",
  "req.typenames": null,
  "req.redist": null,
  "ms.custom": "19H1",
  "f1_keywords": [
    "ID3D11VideoContext1::DecoderUpdateDownsampling",
    "d3d11_1/ID3D11VideoContext1::DecoderUpdateDownsampling"
  ],
  "dev_langs": [
    "c++"
  ],
  "topic_type": [
    "APIRef",
    "kbSyntax"
  ],
  "api_type": [
    "COM"
  ],
  "api_location": [
    "d3d11_1.h"
  ],
  "api_name": [
    "ID3D11VideoContext1.DecoderUpdateDownsampling"
  ]
}