{
  "UID": "NF:azroles.IAzApplication3.OpenScope2",
  "title": "IAzApplication3::OpenScope2 (azroles.h)",
  "description": "Opens an IAzScope2 object with the specified name.",
  "helpviewer_keywords": [
    "IAzApplication3 interface [Security]",
    "OpenScope2 method",
    "IAzApplication3.OpenScope2",
    "IAzApplication3::OpenScope2",
    "OpenScope2",
    "OpenScope2 method [Security]",
    "OpenScope2 method [Security]",
    "IAzApplication3 interface",
    "azroles/IAzApplication3::OpenScope2",
    "security.iazapplication3_openscope2"
  ],
  "old-location": "security\\iazapplication3_openscope2.htm",
  "tech.root": "security",
  "ms.assetid": "1ea9f12e-d00d-4ccd-bfd4-21027610e681",
  "ms.date": "12/05/2018",
  "ms.keywords": "IAzApplication3 interface [Security],OpenScope2 method, IAzApplication3.OpenScope2, IAzApplication3::OpenScope2, OpenScope2, OpenScope2 method [Security], OpenScope2 method [Security],IAzApplication3 interface, azroles/IAzApplication3::OpenScope2, security.iazapplication3_openscope2",
  "req.header": "azroles.h",
  "req.include-header": null,
  "req.target-type": "Windows",
  "req.target-min-winverclnt": "Windows Vista [desktop apps only]",
  "req.target-min-winversvr": "Windows Server 2008 [desktop apps only]",
  "req.kmdf-ver": null,
  "req.umdf-ver": null,
  "req.ddi-compliance": null,
  "req.unicode-ansi": null,
  "req.idl": null,
  "req.max-support": null,
  "req.namespace": null,
  "req.assembly": null,
  "req.type-library": null,
  "req.lib": null,
  "req.dll": "Azroles.dll",
  "req.irql": null,
  "targetos": "Windows",
  "req.typenames": null,
  "req.redist": null,
  "ms.custom": "19H1",
  "f1_keywords": [
    "IAzApplication3::OpenScope2",
    "azroles/IAzApplication3::OpenScope2"
  ],
  "dev_langs": [
    "c++"
  ],
  "topic_type": [
    "APIRef",
    "kbSyntax"
  ],
  "api_type": [
    "COM"
  ],
  "api_location": [
    "Azroles.dll"
  ],
  "api_name": [
    "IAzApplication3.OpenScope2"
  ]
}