{
  "UID": "NS:commctrl._HD_ITEMW",
  "title": "HDITEMW (commctrl.h)",
  "description": "Contains information about an item in a header control. This structure supersedes the HD_ITEM structure. (Unicode)",
  "helpviewer_keywords": [
    "*LPHDITEMW",
    "Combining Flags:",
    "Display:",
    "HDFT_HASNOVALUE",
    "HDFT_ISDATE",
    "HDFT_ISNUMBER",
    "HDFT_ISSTRING",
    "HDF_BITMAP",
    "HDF_BITMAP_ON_RIGHT",
    "HDF_CENTER",
    "HDF_CHECKBOX",
    "HDF_CHECKED",
    "HDF_FIXEDWIDTH",
    "HDF_IMAGE",
    "HDF_JUSTIFYMASK",
    "HDF_LEFT",
    "HDF_OWNERDRAW",
    "HDF_RIGHT",
    "HDF_RTLREADING",
    "HDF_SORTDOWN",
    "HDF_SORTUP",
    "HDF_SPLITBUTTON",
    "HDF_STRING",
    "HDITEM",
    "HDITEM structure [Windows Controls]",
    "HDITEMA",
    "HDITEMW",
    "HDI_BITMAP",
    "HDI_DI_SETITEM",
    "HDI_FILTER",
    "HDI_FORMAT",
    "HDI_HEIGHT",
    "HDI_IMAGE",
    "HDI_LPARAM",
    "HDI_ORDER",
    "HDI_STATE",
    "HDI_TEXT",
    "HDI_WIDTH",
    "LPHDITEM",
    "LPHDITEM structure pointer [Windows Controls]",
    "Text Justification:",
    "_win32_HDITEM",
    "_win32_HDITEM_cpp",
    "commctrl/HDITEM",
    "commctrl/HDITEMA",
    "commctrl/HDITEMW",
    "commctrl/LPHDITEM",
    "controls.HDITEM",
    "controls._win32_HDITEM"
  ],
  "old-location": "controls\\HDITEM.htm",
  "tech.root": "Controls",
  "ms.assetid": "VS|Controls|~\\controls\\header\\structures\\hditem.htm",
  "ms.date": "12/05/2018",
  "ms.keywords": "*LPHDITEMW, Combining Flags:, Display:, HDFT_HASNOVALUE, HDFT_ISDATE, HDFT_ISNUMBER, HDFT_ISSTRING, HDF_BITMAP, HDF_BITMAP_ON_RIGHT, HDF_CENTER, HDF_CHECKBOX, HDF_CHECKED, HDF_FIXEDWIDTH, HDF_IMAGE, HDF_JUSTIFYMASK, HDF_LEFT, HDF_OWNERDRAW, HDF_RIGHT, HDF_RTLREADING, HDF_SORTDOWN, HDF_SORTUP, HDF_SPLITBUTTON, HDF_STRING, HDITEM, HDITEM structure [Windows Controls], HDITEMA, HDITEMW, HDI_BITMAP, HDI_DI_SETITEM, HDI_FILTER, HDI_FORMAT, HDI_HEIGHT, HDI_IMAGE, HDI_LPARAM, HDI_ORDER, HDI_STATE, HDI_TEXT, HDI_WIDTH, LPHDITEM, LPHDITEM structure pointer [Windows Controls], Text Justification:, _win32_HDITEM, _win32_HDITEM_cpp, commctrl/HDITEM, commctrl/HDITEMA, commctrl/HDITEMW, commctrl/LPHDITEM, controls.HDITEM, controls._win32_HDITEM",
  "req.header": "commctrl.h",
  "req.include-header": null,
  "req.target-type": "Windows",
  "req.target-min-winverclnt": "Windows Vista [desktop apps only]",
  "req.target-min-winversvr": "Windows Server 2003 [desktop apps only]",
  "req.kmdf-ver": null,
  "req.umdf-ver": null,
  "req.ddi-compliance": null,
  "req.unicode-ansi": "HDITEMW (Unicode) and HDITEMA (ANSI)",
  "req.idl": null,
  "req.max-support": null,
  "req.namespace": null,
  "req.assembly": null,
  "req.type-library": null,
  "req.lib": null,
  "req.dll": null,
  "req.irql": null,
  "targetos": "Windows",
  "req.typenames": "HDITEMW, *LPHDITEMW",
  "req.redist": null,
  "ms.custom": "19H1",
  "f1_keywords": [
    "_HD_ITEMW",
    "commctrl/_HD_ITEMW",
    "LPHDITEMW",
    "commctrl/LPHDITEMW",
    "HDITEMW",
    "commctrl/HDITEMW"
  ],
  "dev_langs": [
    "c++"
  ],
  "topic_type": [
    "APIRef",
    "kbSyntax"
  ],
  "api_type": [
    "HeaderDef"
  ],
  "api_location": [
    "Commctrl.h"
  ],
  "api_name": [
    "HDITEM",
    "HDITEMA",
    "HDITEMW"
  ]
}